{
  "date": "20260113",
  "items": [
    {
      "ticker": "2330",
      "name": "台積電期貨",
      "data": {
        "top5": {
          "buy": 18600,
          "sell": 24304,
          "net": -5704
        },
        "top10": {
          "buy": 22827,
          "sell": 31926,
          "net": -9099
        },
        "oi": "43968",
        "contract_month": "所有契約"
      }
    },
    {
      "ticker": "2317",
      "name": "鴻海期貨",
      "data": {
        "top5": {
          "buy": 14896,
          "sell": 22633,
          "net": -7737
        },
        "top10": {
          "buy": 19336,
          "sell": 27270,
          "net": -7934
        },
        "oi": "32221",
        "contract_month": "所有契約"
      }
    },
    {
      "ticker": "3231",
      "name": "緯創期貨",
      "data": {
        "top5": {
          "buy": 3806,
          "sell": 6903,
          "net": -3097
        },
        "top10": {
          "buy": 4586,
          "sell": 8333,
          "net": -3747
        },
        "oi": "9676",
        "contract_month": "所有契約"
      }
    },
    {
      "ticker": "2382",
      "name": "廣達期貨",
      "data": {
        "top5": {
          "buy": 2613,
          "sell": 4474,
          "net": -1861
        },
        "top10": {
          "buy": 3098,
          "sell": 4941,
          "net": -1843
        },
        "oi": "5181",
        "contract_month": "所有契約"
      }
    }
  ]
}